{
  "__type__": "cc.SpriteFrame",
  "content": {
    "name": "收藏图标",
    "atlas": "",
    "rect": {
      "x": 0,
      "y": 0,
      "width": 53,
      "height": 56
    },
    "offset": {
      "x": 0,
      "y": 0
    },
    "originalSize": {
      "width": 53,
      "height": 56
    },
    "rotated": false,
    "capInsets": [
      0,
      0,
      0,
      0
    ],
    "vertices": {
      "rawPosition": [
        -26.5,
        -28,
        0,
        26.5,
        -28,
        0,
        -26.5,
        28,
        0,
        26.5,
        28,
        0
      ],
      "indexes": [
        0,
        1,
        2,
        2,
        1,
        3
      ],
      "uv": [
        0,
        56,
        53,
        56,
        0,
        0,
        53,
        0
      ],
      "nuv": [
        0,
        0,
        1,
        0,
        0,
        1,
        1,
        1
      ],
      "minPos": {
        "x": -26.5,
        "y": -28,
        "z": 0
      },
      "maxPos": {
        "x": 26.5,
        "y": 28,
        "z": 0
      }
    },
    "texture": "676bade0-9e65-420f-b5af-e2c33a860184@6c48a",
    "packable": true,
    "pixelsToUnit": 100,
    "pivot": {
      "x": 0.5,
      "y": 0.5
    },
    "meshType": 0
  }
}